{
	"name": "Parquet4",
	"properties": {
		"linkedServiceName": {
			"referenceName": "HttpServer3",
			"type": "LinkedServiceReference"
		},
		"parameters": {
			"month": {
				"type": "String"
			}
		},
		"annotations": [],
		"type": "Parquet",
		"typeProperties": {
			"location": {
				"type": "HttpServerLocation",
				"relativeUrl": {
					"value": "trip-data/green_tripdata_2023-@{dataset().month}.parquet",
					"type": "Expression"
				}
			},
			"compressionCodec": "snappy"
		},
		"schema": []
	}
}